agentkernel/__init__.py
agentkernel/_config.py
agentkernel/async_client.py
agentkernel/client.py
agentkernel/errors.py
agentkernel/py.typed
agentkernel/sse.py
agentkernel/types.py
agentkernel_sdk-0.5.1.dist-info/METADATA
agentkernel_sdk-0.5.1.dist-info/WHEEL
agentkernel_sdk-0.5.1.dist-info/RECORD
