Metadata-Version: 2.4
Name: agentkernel-sdk
Version: 0.5.1
Summary: Python SDK for agentkernel — run AI coding agents in secure, isolated microVMs
Project-URL: Homepage, https://github.com/thrashr888/agentkernel
Project-URL: Repository, https://github.com/thrashr888/agentkernel/tree/main/sdk/python
Author-email: Paul Thrasher <thrashr888@gmail.com>
License-Expression: MIT
Keywords: agent,agentkernel,ai,firecracker,microvm,sandbox
Classifier: Development Status :: 3 - Alpha
Classifier: Intended Audience :: Developers
Classifier: License :: OSI Approved :: MIT License
Classifier: Programming Language :: Python :: 3
Classifier: Programming Language :: Python :: 3.10
Classifier: Programming Language :: Python :: 3.11
Classifier: Programming Language :: Python :: 3.12
Classifier: Programming Language :: Python :: 3.13
Classifier: Programming Language :: Python :: 3.14
Classifier: Typing :: Typed
Requires-Python: >=3.10
Requires-Dist: httpx-sse>=0.4
Requires-Dist: httpx>=0.27
Requires-Dist: pydantic>=2.0
Provides-Extra: dev
Requires-Dist: mypy>=1.13; extra == 'dev'
Requires-Dist: pytest-asyncio>=0.24; extra == 'dev'
Requires-Dist: pytest-httpx>=0.34; extra == 'dev'
Requires-Dist: pytest>=8.0; extra == 'dev'
Requires-Dist: ruff>=0.8; extra == 'dev'
